bibtex_clean/__init__.py
bibtex_clean/_version.py
bibtex_clean/clean.py
bibtex_clean/cli.py
bibtex_clean/hardcoded_words.py
bibtex_clean/title_styler.py
bibtex_clean/__pycache__/__init__.cpython-310.pyc
bibtex_clean/__pycache__/__init__.cpython-311.pyc
bibtex_clean/__pycache__/_version.cpython-311.pyc
bibtex_clean/__pycache__/clean.cpython-310.pyc
bibtex_clean/__pycache__/clean.cpython-311.pyc
bibtex_clean/__pycache__/cli.cpython-310.pyc
bibtex_clean/__pycache__/cli.cpython-311.pyc
bibtex_clean/__pycache__/hardcoded_words.cpython-310.pyc
bibtex_clean/__pycache__/hardcoded_words.cpython-311.pyc
bibtex_clean/__pycache__/title_styler.cpython-310.pyc
bibtex_clean/__pycache__/title_styler.cpython-311.pyc
bibtex_clean/style_fields/aer.json
bibtex_clean/style_fields/jpe.json
bibtex_clean-0.0.5.dist-info/METADATA
bibtex_clean-0.0.5.dist-info/WHEEL
bibtex_clean-0.0.5.dist-info/entry_points.txt
bibtex_clean-0.0.5.dist-info/top_level.txt
bibtex_clean-0.0.5.dist-info/RECORD
