Metadata-Version: 2.1
Name: bibtex-clean
Version: 0.0.5
Summary: CLI utility to clean bibtex files.
Home-page: https://github.com/CangyuanLi/bibtex_fields
Author: Cangyuan Li
Author-email: everest229@gmail.com
License: MIT
Classifier: Programming Language :: Python :: 3
Classifier: License :: OSI Approved :: MIT License
Classifier: Operating System :: OS Independent
Requires-Dist: bibtexparser
Requires-Dist: colorama
Requires-Dist: pycutils
